{
	"errcode":0,
	"success":[
       {
       	 "id":1,
         "name":"西少爷肉夹馍",
         "img":"img/1.jpg",
         "start":5,
         "sales":147,
         "startTip":20,
         "tip":5,
         "time":30,
         "goods":{
         	"热销菜品":[
               {
                 "foodName":"黑椒牛柳套餐",
                 "foodImg":"img/f01.jpg",
                 "foodSale":301,
                 "good":2,
                 "price":25
               },
               {
                 "foodName":"黑椒牛柳套餐",
                 "foodImg":"img/f01.jpg",
                 "foodSale":301,
                 "good":2,
                 "price":25
               },
               {
                 "foodName":"黑椒牛柳套餐",
                 "foodImg":"img/f01.jpg",
                 "foodSale":301,
                 "good":2,
                 "price":25
               },
               {
                 "foodName":"黑椒牛柳套餐",
                 "foodImg":"img/f01.jpg",
                 "foodSale":301,
                 "good":2,
                 "price":25
               }
         	],
         	"经典套餐":[
               {
                 "foodName":"黑椒牛柳套餐",
                 "foodImg":"img/f01.jpg",
                 "foodSale":301,
                 "good":2,
                 "price":25
               },
               {
                 "foodName":"黑椒牛柳套餐",
                 "foodImg":"img/f01.jpg",
                 "foodSale":301,
                 "good":2,
                 "price":25
               },
               {
                 "foodName":"黑椒牛柳套餐",
                 "foodImg":"img/f01.jpg",
                 "foodSale":301,
                 "good":2,
                 "price":25
               }
         	],
         	"凉菜":[
               {
                 "foodName":"黑椒牛柳套餐",
                 "foodImg":"img/f01.jpg",
                 "foodSale":301,
                 "good":2,
                 "price":25
               },
               {
                 "foodName":"黑椒牛柳套餐",
                 "foodImg":"img/f01.jpg",
                 "foodSale":301,
                 "good":2,
                 "price":25
               },
               {
                 "foodName":"黑椒牛柳套餐",
                 "foodImg":"img/f01.jpg",
                 "foodSale":301,
                 "good":2,
                 "price":25
               }
         	],
            "砂锅":[
               {
                 "foodName":"黑椒牛柳套餐",
                 "foodImg":"img/f01.jpg",
                 "foodSale":301,
                 "good":2,
                 "price":25
               },
               {
                 "foodName":"黑椒牛柳套餐",
                 "foodImg":"img/f01.jpg",
                 "foodSale":301,
                 "good":2,
                 "price":25
               },
               {
                 "foodName":"黑椒牛柳套餐",
                 "foodImg":"img/f01.jpg",
                 "foodSale":301,
                 "good":2,
                 "price":25
               },
               {
                 "foodName":"黑椒牛柳套餐",
                 "foodImg":"img/f01.jpg",
                 "foodSale":301,
                 "good":2,
                 "price":25
               }
         	],
         	"进口小吃":[
               {
                 "foodName":"黑椒牛柳套餐",
                 "foodImg":"img/f01.jpg",
                 "foodSale":301,
                 "good":2,
                 "price":25
               },
              {
                "foodName":"黑椒牛柳套餐",
                "foodImg":"img/f01.jpg",
                "foodSale":301,
                "good":2,
                "price":25
              },
               {
                 "foodName":"黑椒牛柳套餐",
                 "foodImg":"img/f01.jpg",
                 "foodSale":301,
                 "good":2,
                 "price":25
               },
              {
                "foodName":"黑椒牛柳套餐",
                "foodImg":"img/f01.jpg",
                "foodSale":301,
                "good":2,
                "price":25
              },
              {
                "foodName":"黑椒牛柳套餐",
                "foodImg":"img/f01.jpg",
                "foodSale":301,
                "good":2,
                "price":25
              },
               {
                 "foodName":"黑椒牛柳套餐",
                 "foodImg":"img/f01.jpg",
                 "foodSale":301,
                 "good":2,
                 "price":25
               },
              {
                "foodName":"黑椒牛柳套餐",
                "foodImg":"img/f01.jpg",
                "foodSale":301,
                "good":2,
                "price":25
              },
              {
                "foodName":"黑椒牛柳套餐",
                "foodImg":"img/f01.jpg",
                "foodSale":301,
                "good":2,
                "price":25
              },
              {
                "foodName":"黑椒牛柳套餐",
                "foodImg":"img/f01.jpg",
                "foodSale":301,
                "good":2,
                "price":25
              }
         	]
         }
       },
       {
       	 "id":2,
         "name":"汤城小厨",
         "img":"img/2.jpg",
         "start":5,
         "sales":158,
         "startTip":25,
         "tip":6,
         "time":25,
         "goods":{
         	"热销菜品":[
               {
                 "foodName":"黑椒牛柳套餐",
                 "foodImg":"img/f01.jpg",
                 "foodSale":301,
                 "good":2,
                 "price":25
               },
               {
                 "foodName":"黑椒牛柳套餐",
                 "foodImg":"img/f01.jpg",
                 "foodSale":301,
                 "good":2,
                 "price":25
               },
               {
                 "foodName":"黑椒牛柳套餐",
                 "foodImg":"img/f01.jpg",
                 "foodSale":301,
                 "good":2,
                 "price":25
               },
               {
                 "foodName":"黑椒牛柳套餐",
                 "foodImg":"img/f01.jpg",
                 "foodSale":301,
                 "good":2,
                 "price":25
               }
         	],
         	"经典套餐":[
               {
                 "foodName":"黑椒牛柳套餐",
                 "foodImg":"img/f01.jpg",
                 "foodSale":301,
                 "good":2,
                 "price":25
               },
               {
                 "foodName":"黑椒牛柳套餐",
                 "foodImg":"img/f01.jpg",
                 "foodSale":301,
                 "good":2,
                 "price":25
               },
               {
                 "foodName":"黑椒牛柳套餐",
                 "foodImg":"img/f01.jpg",
                 "foodSale":301,
                 "good":2,
                 "price":25
               }
         	],
         	"凉菜":[
               {
                 "foodName":"黑椒牛柳套餐",
                 "foodImg":"img/f01.jpg",
                 "foodSale":301,
                 "good":2,
                 "price":25
               },
               {
                 "foodName":"黑椒牛柳套餐",
                 "foodImg":"img/f01.jpg",
                 "foodSale":301,
                 "good":2,
                 "price":25
               },
               {
                 "foodName":"黑椒牛柳套餐",
                 "foodImg":"img/f01.jpg",
                 "foodSale":301,
                 "good":2,
                 "price":25
               }
         	],
         	"进口小吃":[
               {
                 "foodName":"黑椒牛柳套餐",
                 "foodImg":"img/f01.jpg",
                 "foodSale":301,
                 "good":2,
                 "price":25
               },
               {
                 "foodName":"黑椒牛柳套餐",
                 "foodImg":"img/f01.jpg",
                 "foodSale":301,
                 "good":2,
                 "price":25
               },
               {
                 "foodName":"黑椒牛柳套餐",
                 "foodImg":"img/f01.jpg",
                 "foodSale":301,
                 "good":2,
                 "price":25
               },
              {
                "foodName":"黑椒牛柳套餐",
                "foodImg":"img/f01.jpg",
                "foodSale":301,
                "good":2,
                "price":25
              },
              {
                "foodName":"黑椒牛柳套餐",
                "foodImg":"img/f01.jpg",
                "foodSale":301,
                "good":2,
                "price":25
              },
              {
                "foodName":"黑椒牛柳套餐",
                "foodImg":"img/f01.jpg",
                "foodSale":301,
                "good":2,
                "price":25
              },
              {
                "foodName":"黑椒牛柳套餐",
                "foodImg":"img/f01.jpg",
                "foodSale":301,
                "good":2,
                "price":25
              },
              {
                "foodName":"黑椒牛柳套餐",
                "foodImg":"img/f01.jpg",
                "foodSale":301,
                "good":2,
                "price":25
              }
         	]
         }
       },
       {
       	 "id":3,
         "name":"麦咖啡(新中关店)",
         "img":"img/3.jpg",
         "start":5,
         "sales":120,
         "startTip":22,
         "tip":2,
         "time":28,
         "goods":{
         	"热销菜品":[
               {
                 "foodName":"黑椒牛柳套餐",
                 "foodImg":"img/f01.jpg",
                 "foodSale":301,
                 "good":2,
                 "price":25
               },
               {
                 "foodName":"黑椒牛柳套餐",
                 "foodImg":"img/f01.jpg",
                 "foodSale":301,
                 "good":2,
                 "price":25
               },
               {
                 "foodName":"黑椒牛柳套餐",
                 "foodImg":"img/f01.jpg",
                 "foodSale":301,
                 "good":2,
                 "price":25
               },
               {
                 "foodName":"黑椒牛柳套餐",
                 "foodImg":"img/f01.jpg",
                 "foodSale":301,
                 "good":2,
                 "price":25
               }
         	],
         	"经典套餐":[
               {
                 "foodName":"黑椒牛柳套餐",
                 "foodImg":"img/f01.jpg",
                 "foodSale":301,
                 "good":2,
                 "price":25
               },
               {
                 "foodName":"黑椒牛柳套餐",
                 "foodImg":"img/f01.jpg",
                 "foodSale":301,
                 "good":2,
                 "price":25
               },
               {
                 "foodName":"黑椒牛柳套餐",
                 "foodImg":"img/f01.jpg",
                 "foodSale":301,
                 "good":2,
                 "price":25
               }
         	],
            "砂锅":[
               {
                 "foodName":"黑椒牛柳套餐",
                 "foodImg":"img/f01.jpg",
                 "foodSale":301,
                 "good":2,
                 "price":25
               },
               {
                 "foodName":"黑椒牛柳套餐",
                 "foodImg":"img/f01.jpg",
                 "foodSale":301,
                 "good":2,
                 "price":25
               },
               {
                 "foodName":"黑椒牛柳套餐",
                 "foodImg":"img/f01.jpg",
                 "foodSale":301,
                 "good":2,
                 "price":25
               }
         	],
         	"进口小吃":[
               {
                 "foodName":"黑椒牛柳套餐",
                 "foodImg":"img/f01.jpg",
                 "foodSale":301,
                 "good":2,
                 "price":25
               },
              {
                "foodName":"黑椒牛柳套餐",
                "foodImg":"img/f01.jpg",
                "foodSale":301,
                "good":2,
                "price":25
              },
               {
                 "foodName":"黑椒牛柳套餐",
                 "foodImg":"img/f01.jpg",
                 "foodSale":301,
                 "good":2,
                 "price":25
               },
              {
                "foodName":"黑椒牛柳套餐",
                "foodImg":"img/f01.jpg",
                "foodSale":301,
                "good":2,
                "price":25
              },
              {
                "foodName":"黑椒牛柳套餐",
                "foodImg":"img/f01.jpg",
                "foodSale":301,
                "good":2,
                "price":25
              },
               {
                 "foodName":"黑椒牛柳套餐",
                 "foodImg":"img/f01.jpg",
                 "foodSale":301,
                 "good":2,
                 "price":25
               },
              {
                "foodName":"黑椒牛柳套餐",
                "foodImg":"img/f01.jpg",
                "foodSale":301,
                "good":2,
                "price":25
              },
              {
                "foodName":"黑椒牛柳套餐",
                "foodImg":"img/f01.jpg",
                "foodSale":301,
                "good":2,
                "price":25
              }
         	]
         }
       },
       {
       	 "id":4,
         "name":"四爷牛拉中关村旗舰店",
         "img":"img/4.jpg",
         "start":5,
         "sales":165,
         "startTip":28,
         "tip":0,
         "time":22,
         "goods":{
         	"热销菜品":[
               {
                 "foodName":"黑椒牛柳套餐",
                 "foodImg":"img/f01.jpg",
                 "foodSale":301,
                 "good":2,
                 "price":25
               },
               {
                 "foodName":"黑椒牛柳套餐",
                 "foodImg":"img/f01.jpg",
                 "foodSale":301,
                 "good":2,
                 "price":25
               },
               {
                 "foodName":"黑椒牛柳套餐",
                 "foodImg":"img/f01.jpg",
                 "foodSale":301,
                 "good":2,
                 "price":25
               },
               {
                 "foodName":"黑椒牛柳套餐",
                 "foodImg":"img/f01.jpg",
                 "foodSale":301,
                 "good":2,
                 "price":25
               }
         	],
         	"经典套餐":[
               {
                 "foodName":"黑椒牛柳套餐",
                 "foodImg":"img/f01.jpg",
                 "foodSale":301,
                 "good":2,
                 "price":25
               },
               {
                 "foodName":"黑椒牛柳套餐",
                 "foodImg":"img/f01.jpg",
                 "foodSale":301,
                 "good":2,
                 "price":25
               },
               {
                 "foodName":"黑椒牛柳套餐",
                 "foodImg":"img/f01.jpg",
                 "foodSale":301,
                 "good":2,
                 "price":25
               }
         	],
            "砂锅":[
               {
                 "foodName":"黑椒牛柳套餐",
                 "foodImg":"img/f01.jpg",
                 "foodSale":301,
                 "good":2,
                 "price":25
               },
               {
                 "foodName":"黑椒牛柳套餐",
                 "foodImg":"img/f01.jpg",
                 "foodSale":301,
                 "good":2,
                 "price":25
               },
               {
                 "foodName":"黑椒牛柳套餐",
                 "foodImg":"img/f01.jpg",
                 "foodSale":301,
                 "good":2,
                 "price":25
               },
               {
                 "foodName":"黑椒牛柳套餐",
                 "foodImg":"img/f01.jpg",
                 "foodSale":301,
                 "good":2,
                 "price":25
               }
         	]
         }
       },
       {
       	 "id":5,
         "name":"真功夫(新中关店)",
         "img":"img/5.jpg",
         "start":5,
         "sales":112,
         "startTip":15,
         "tip":4,
         "time":35,
         "goods":{
         	"热销菜品":[
               {
                 "foodName":"黑椒牛柳套餐",
                 "foodImg":"img/f01.jpg",
                 "foodSale":301,
                 "good":2,
                 "price":25
               },
               {
                 "foodName":"黑椒牛柳套餐",
                 "foodImg":"img/f01.jpg",
                 "foodSale":301,
                 "good":2,
                 "price":25
               },
               {
                 "foodName":"黑椒牛柳套餐",
                 "foodImg":"img/f01.jpg",
                 "foodSale":301,
                 "good":2,
                 "price":25
               },
               {
                 "foodName":"黑椒牛柳套餐",
                 "foodImg":"img/f01.jpg",
                 "foodSale":301,
                 "good":2,
                 "price":25
               }
         	],
         	"经典套餐":[
               {
                 "foodName":"黑椒牛柳套餐",
                 "foodImg":"img/f01.jpg",
                 "foodSale":301,
                 "good":2,
                 "price":25
               },
               {
                 "foodName":"黑椒牛柳套餐",
                 "foodImg":"img/f01.jpg",
                 "foodSale":301,
                 "good":2,
                 "price":25
               },
               {
                 "foodName":"黑椒牛柳套餐",
                 "foodImg":"img/f01.jpg",
                 "foodSale":301,
                 "good":2,
                 "price":25
               }
         	],
         	"凉菜":[
               {
                 "foodName":"黑椒牛柳套餐",
                 "foodImg":"img/f01.jpg",
                 "foodSale":301,
                 "good":2,
                 "price":25
               },
               {
                 "foodName":"黑椒牛柳套餐",
                 "foodImg":"img/f01.jpg",
                 "foodSale":301,
                 "good":2,
                 "price":25
               },
               {
                 "foodName":"黑椒牛柳套餐",
                 "foodImg":"img/f01.jpg",
                 "foodSale":301,
                 "good":2,
                 "price":25
               }
         	],
            "砂锅":[
               {
                 "foodName":"黑椒牛柳套餐",
                 "foodImg":"img/f01.jpg",
                 "foodSale":301,
                 "good":2,
                 "price":25
               },
               {
                 "foodName":"黑椒牛柳套餐",
                 "foodImg":"img/f01.jpg",
                 "foodSale":301,
                 "good":2,
                 "price":25
               },
               {
                 "foodName":"黑椒牛柳套餐",
                 "foodImg":"img/f01.jpg",
                 "foodSale":301,
                 "good":2,
                 "price":25
               },
               {
                 "foodName":"黑椒牛柳套餐",
                 "foodImg":"img/f01.jpg",
                 "foodSale":301,
                 "good":2,
                 "price":25
               }
         	],
         	"进口小吃":[
               {
                 "foodName":"黑椒牛柳套餐",
                 "foodImg":"img/f01.jpg",
                 "foodSale":301,
                 "good":2,
                 "price":25
               },
               {
                 "foodName":"黑椒牛柳套餐",
                 "foodImg":"img/f01.jpg",
                 "foodSale":301,
                 "good":2,
                 "price":25
               },
              {
                "foodName":"黑椒牛柳套餐",
                "foodImg":"img/f01.jpg",
                "foodSale":301,
                "good":2,
                "price":25
              },
              {
                "foodName":"黑椒牛柳套餐",
                "foodImg":"img/f01.jpg",
                "foodSale":301,
                "good":2,
                "price":25
              },
              {
                "foodName":"黑椒牛柳套餐",
                "foodImg":"img/f01.jpg",
                "foodSale":301,
                "good":2,
                "price":25
              },
               {
                 "foodName":"黑椒牛柳套餐",
                 "foodImg":"img/f01.jpg",
                 "foodSale":301,
                 "good":2,
                 "price":25
               },
              {
                "foodName":"黑椒牛柳套餐",
                "foodImg":"img/f01.jpg",
                "foodSale":301,
                "good":2,
                "price":25
              },
              {
                "foodName":"黑椒牛柳套餐",
                "foodImg":"img/f01.jpg",
                "foodSale":301,
                "good":2,
                "price":25
              }
         	]
         }
       }
	]
}